queezer/__init__.py
queezer/storage/adapter_interface.py
queezer/storage/queezer_api.py
queezer/storage/sqlite.py
queezer/utils.py
queezer-0.1.0.dist-info/LICENSE
queezer-0.1.0.dist-info/METADATA
queezer-0.1.0.dist-info/WHEEL
queezer-0.1.0.dist-info/RECORD
