Metadata-Version: 2.1
Name: queezer
Version: 0.1.0
Summary: Queezer is designed to help you start owning your own LLM models by collecting request and response data from API calls.
Author: MLalex
Author-email: consai.alex@gmail.com
Requires-Python: >=3.9,<4.0
Classifier: Development Status :: 4 - Beta
Classifier: Intended Audience :: Developers
Classifier: License :: OSI Approved :: MIT License
Classifier: Programming Language :: Python :: 3
Classifier: Programming Language :: Python :: 3.9
Classifier: Programming Language :: Python :: 3.10
Classifier: Programming Language :: Python :: 3.11
Classifier: Programming Language :: Python :: 3.12
Requires-Dist: requests (>=2.32.3,<3.0.0)
Project-URL: Issue Tracker, https://github.com/JavAmz/queezer/issues
Project-URL: Source, https://github.com/JavAmz/queezer
